{
    "limit": 100,
    "total_count": 12,
    "first": {
        "href": "https://eu-de.apprapp.cloud.ibm.com/apprapp/config_aggregator/v1/instances/e27c1acc-eaa9-42c3-85c2-b30831a59c39/configs?limit=100"
    },
    "configs": [
        {
            "about": {
                "access_tags": [],
                "account_id": "3a4ef740c2d607b1331738faf667de76",
                "config_type": "image",
                "last_config_refresh_time": "2025-05-09T05:03:08Z",
                "location": "eu-de-3",
                "resource_crn": "crn:v1:bluemix:public:is:eu-de:a/811f8abfbd32425597dc7ba40da98fa6::instance_image:02d7_43f05bc3-7e36-4bbe-a88d-173f83ade9b6_r010-9af3670c-99c7-4f14-9bd3-ce6390cb1d70",
                "resource_group_id": "438b802f75874f69b7a7abeb8d5269e4",
                "resource_name": "",
                "service_name": "is.instance",
                "service_tags": [],
                "user_tags": []
            },
            "config": {
                "customer_defined_image": false,
                "image_crn": "crn:v1:bluemix:public:is:eu-de:a/811f8abfbd32425597dc7ba40da98fa6::image:r010-9af3670c-99c7-4f14-9bd3-ce6390cb1d70",
                "image_encryption": "none",
                "image_name": "ibm-windows-server-2022-full-standard-amd64-16",
                "image_visibility": "public",
                "resource_id": "02d7_43f05bc3-7e36-4bbe-a88d-173f83ade9b6",
                "vpc_id": "r010-38f27614-a821-4604-848b-4f04fd1460c9"
            },
            "config_v2": {}
        },
        {
            "about": {
                "access_tags": [],
                "account_id": "3a4ef740c2d607b1331738faf667de76",
                "config_type": "image",
                "last_config_refresh_time": "2025-05-08T21:11:15Z",
                "location": "eu-de-2",
                "resource_crn": "crn:v1:bluemix:public:is:eu-de:a/811f8abfbd32425597dc7ba40da98fa6::instance_image:02c7_4838ec5d-7075-414b-aa43-b705d0e39fd1_r010-217d7246-ae83-4a55-8c66-f57b6e2a00c6",
                "resource_group_id": "768fdf7e87f44ab2bfec4e6b910f1cfb",
                "resource_name": "",
                "service_name": "is.instance",
                "service_tags": [],
                "user_tags": []
            },
            "config": {
                "customer_defined_image": false,
                "image_crn": "crn:v1:bluemix:public:is:eu-de:a/811f8abfbd32425597dc7ba40da98fa6::image:r010-217d7246-ae83-4a55-8c66-f57b6e2a00c6",
                "image_encryption": "none",
                "image_name": "ibm-redhat-9-4-minimal-amd64-5",
                "image_visibility": "public",
                "resource_id": "02c7_4838ec5d-7075-414b-aa43-b705d0e39fd1",
                "vpc_id": "r010-3961aa14-c59a-420a-8cbb-d2c27a304f1f"
            },
            "config_v2": {}
        },
        {
            "about": {
                "access_tags": [],
                "account_id": "3a4ef740c2d607b1331738faf667de76",
                "config_type": "instance",
                "last_config_refresh_time": "2025-05-09T05:03:08Z",
                "location": "eu-de-3",
                "resource_crn": "crn:v1:bluemix:public:is:eu-de-3:a/3a4ef740c2d607b1331738faf667de76::instance:02d7_43f05bc3-7e36-4bbe-a88d-173f83ade9b6",
                "resource_group_id": "438b802f75874f69b7a7abeb8d5269e4",
                "resource_name": "billingcognos",
                "service_name": "is.instance",
                "service_tags": [],
                "user_tags": []
            },
            "config": {
                "all_network_interfaces_sg_found": true,
                "allow_ip_spoofing": false,
                "cbr_check_enforced": "cbr",
                "cbr_enabled": false,
                "cbr_private_public_allowed_ip_list": [],
                "count_sg_network_interfaces": 1,
                "default_cbr_mfa_enabled": "OFF",
                "default_netmask_bits_length": 256,
                "endpoints_restricted": false,
                "floating_ip_found": true,
                "max_netmask_bits_length": 0,
                "network_interfaces_sg_found": true,
                "public_endpoints_mfa_enabled": "OFF",
                "resource_id": "02d7_43f05bc3-7e36-4bbe-a88d-173f83ade9b6",
                "resource_name": "billingcognos",
                "restricts_private_endpoints": false,
                "vm_image_name": "ibm-windows-server-2022-full-standard-amd64-16",
                "vpc_id": "r010-38f27614-a821-4604-848b-4f04fd1460c9",
                "wild_card_in_private_list": false,
                "wild_card_in_public_list": false
            },
            "config_v2": {}
        },
        {
            "about": {
                "access_tags": [],
                "account_id": "3a4ef740c2d607b1331738faf667de76",
                "config_type": "volume",
                "last_config_refresh_time": "2025-05-09T05:03:08Z",
                "location": "eu-de-3",
                "resource_crn": "crn:v1:bluemix:public:is:eu-de-3:a/3a4ef740c2d607b1331738faf667de76::instance_volume:02d7_43f05bc3-7e36-4bbe-a88d-173f83ade9b6_r010-e58d88f9-1c13-4ddc-93e9-897ab3cef632",
                "resource_group_id": "438b802f75874f69b7a7abeb8d5269e4",
                "resource_name": "",
                "service_name": "is.instance",
                "service_tags": [],
                "user_tags": []
            },
            "config": {
                "cbr_enabled": false,
                "resource_id": "02d7_43f05bc3-7e36-4bbe-a88d-173f83ade9b6",
                "volume_encryption": "provider_managed",
                "volume_encryption_key_crn": "",
                "volume_type": "boot",
                "vpc_id": "r010-38f27614-a821-4604-848b-4f04fd1460c9"
            },
            "config_v2": {}
        },
        {
            "about": {
                "access_tags": [],
                "account_id": "3a4ef740c2d607b1331738faf667de76",
                "config_type": "instance",
                "last_config_refresh_time": "2025-05-08T21:11:15Z",
                "location": "eu-de-2",
                "resource_crn": "crn:v1:bluemix:public:is:eu-de-2:a/3a4ef740c2d607b1331738faf667de76::instance:02c7_4838ec5d-7075-414b-aa43-b705d0e39fd1",
                "resource_group_id": "768fdf7e87f44ab2bfec4e6b910f1cfb",
                "resource_name": "fq-datastage",
                "service_name": "is.instance",
                "service_tags": [],
                "user_tags": []
            },
            "config": {
                "all_network_interfaces_sg_found": true,
                "allow_ip_spoofing": false,
                "cbr_check_enforced": "cbr",
                "cbr_enabled": false,
                "cbr_private_public_allowed_ip_list": [],
                "count_sg_network_interfaces": 1,
                "default_cbr_mfa_enabled": "OFF",
                "default_netmask_bits_length": 256,
                "endpoints_restricted": false,
                "floating_ip_found": true,
                "max_netmask_bits_length": 0,
                "network_interfaces_sg_found": true,
                "public_endpoints_mfa_enabled": "OFF",
                "resource_id": "02c7_4838ec5d-7075-414b-aa43-b705d0e39fd1",
                "resource_name": "fq-datastage",
                "restricts_private_endpoints": false,
                "vm_image_name": "ibm-redhat-9-4-minimal-amd64-5",
                "vpc_id": "r010-3961aa14-c59a-420a-8cbb-d2c27a304f1f",
                "wild_card_in_private_list": false,
                "wild_card_in_public_list": false
            },
            "config_v2": {}
        },
        {
            "about": {
                "access_tags": [],
                "account_id": "3a4ef740c2d607b1331738faf667de76",
                "config_type": "volume",
                "last_config_refresh_time": "2025-05-08T21:11:15Z",
                "location": "eu-de-2",
                "resource_crn": "crn:v1:bluemix:public:is:eu-de-2:a/3a4ef740c2d607b1331738faf667de76::instance_volume:02c7_4838ec5d-7075-414b-aa43-b705d0e39fd1_r010-80bddfd4-db50-43dd-9692-472831142df0",
                "resource_group_id": "768fdf7e87f44ab2bfec4e6b910f1cfb",
                "resource_name": "",
                "service_name": "is.instance",
                "service_tags": [],
                "user_tags": []
            },
            "config": {
                "cbr_enabled": false,
                "resource_id": "02c7_4838ec5d-7075-414b-aa43-b705d0e39fd1",
                "volume_encryption": "provider_managed",
                "volume_encryption_key_crn": "",
                "volume_type": "boot",
                "vpc_id": "r010-3961aa14-c59a-420a-8cbb-d2c27a304f1f"
            },
            "config_v2": {}
        },
        {
            "about": {
                "access_tags": null,
                "account_id": "3a4ef740c2d607b1331738faf667de76",
                "config_type": "network-interface",
                "created_at": "2025-02-03T17:00:19.000Z",
                "last_config_refresh_time": "2025-05-05T22:39:29.324353402Z",
                "location": "eu-de",
                "resource_crn": "crn:v1:bluemix:public:is:eu-de-2:a/3a4ef740c2d607b1331738faf667de76::instance:02c7_4838ec5d-7075-414b-aa43-b705d0e39fd1",
                "resource_group_id": "768fdf7e87f44ab2bfec4e6b910f1cfb",
                "resource_name": "eth0",
                "service_name": "is.instance",
                "service_tags": null,
                "type_id": "02c7-442e8ba1-d8a7-4b47-bdd2-1a0f9a7fe868",
                "user_tags": null
            },
            "config": null,
            "config_v2": {
                "allow_ip_spoofing": false,
                "floating_ips": [
                    {
                        "address": "158.176.9.7",
                        "crn": "crn:v1:bluemix:public:is:eu-de-2:a/3a4ef740c2d607b1331738faf667de76::floating-ip:r010-f1d96e27-18d8-4bcf-a4ad-7d81dcb2765e",
                        "deleted": [],
                        "href": "https://eu-de.private.iaas.cloud.ibm.com/v1/floating_ips/r010-f1d96e27-18d8-4bcf-a4ad-7d81dcb2765e",
                        "id": "r010-f1d96e27-18d8-4bcf-a4ad-7d81dcb2765e",
                        "name": "tuvu"
                    }
                ],
                "href": "https://eu-de.private.iaas.cloud.ibm.com/v1/instances/02c7_4838ec5d-7075-414b-aa43-b705d0e39fd1/network_interfaces/02c7-442e8ba1-d8a7-4b47-bdd2-1a0f9a7fe868",
                "port_speed": 6000,
                "primary_ip": [
                    {
                        "address": "10.243.64.4",
                        "href": "https://eu-de.private.iaas.cloud.ibm.com/v1/subnets/02c7-f27e1e0d-290b-440a-8be9-7f20ed5e333a/reserved_ips/02c7-a09981c8-5e7a-4e13-b124-7223994c13e2",
                        "name": "manifesto-tilt-hamster-bovine",
                        "reserved_ip": "02c7-a09981c8-5e7a-4e13-b124-7223994c13e2",
                        "resource_type": "subnet_reserved_ip"
                    }
                ],
                "primary_ipv4_address": "10.243.64.4",
                "reserved_ips": [
                    {
                        "address": "10.243.64.4",
                        "auto_delete": true,
                        "created_at": "2025-02-03T17:00:20.000Z",
                        "href": "https://eu-de.private.iaas.cloud.ibm.com/v1/subnets/02c7-f27e1e0d-290b-440a-8be9-7f20ed5e333a/reserved_ips/02c7-a09981c8-5e7a-4e13-b124-7223994c13e2",
                        "name": "manifesto-tilt-hamster-bovine",
                        "owner": "user",
                        "reserved_ip": "02c7-a09981c8-5e7a-4e13-b124-7223994c13e2",
                        "resource_type": "subnet_reserved_ip",
                        "target": "02c7-442e8ba1-d8a7-4b47-bdd2-1a0f9a7fe868"
                    }
                ],
                "resource_type": "network_interface",
                "security_groups": [
                    {
                        "crn": "crn:v1:bluemix:public:is:eu-de:a/3a4ef740c2d607b1331738faf667de76::security-group:r010-5b4dec7e-faf5-426b-820e-5e8d2faf9a4d",
                        "deleted": [],
                        "href": "https://eu-de.private.iaas.cloud.ibm.com/v1/security_groups/r010-5b4dec7e-faf5-426b-820e-5e8d2faf9a4d",
                        "id": "r010-5b4dec7e-faf5-426b-820e-5e8d2faf9a4d",
                        "name": "fq414-vpc-sg"
                    }
                ],
                "status": "available",
                "subnet": [
                    {
                        "crn": "crn:v1:bluemix:public:is:eu-de-2:a/3a4ef740c2d607b1331738faf667de76::subnet:02c7-f27e1e0d-290b-440a-8be9-7f20ed5e333a",
                        "deleted": [],
                        "href": "https://eu-de.private.iaas.cloud.ibm.com/v1/subnets/02c7-f27e1e0d-290b-440a-8be9-7f20ed5e333a",
                        "id": "02c7-f27e1e0d-290b-440a-8be9-7f20ed5e333a",
                        "name": "fq414-subnet-2"
                    }
                ],
                "type": "primary"
            }
        },
        {
            "about": {
                "access_tags": null,
                "account_id": "3a4ef740c2d607b1331738faf667de76",
                "config_type": "network-attachment",
                "created_at": "2025-02-03T17:00:19.000Z",
                "last_config_refresh_time": "2025-05-05T22:39:29.324353402Z",
                "location": "eu-de",
                "resource_crn": "crn:v1:bluemix:public:is:eu-de-2:a/3a4ef740c2d607b1331738faf667de76::instance:02c7_4838ec5d-7075-414b-aa43-b705d0e39fd1",
                "resource_group_id": "768fdf7e87f44ab2bfec4e6b910f1cfb",
                "resource_name": "eth0",
                "service_name": "is.instance",
                "service_tags": null,
                "type_id": "02c7-442e8ba1-d8a7-4b47-bdd2-1a0f9a7fe868",
                "user_tags": null
            },
            "config": null,
            "config_v2": {
                "href": "https://eu-de.private.iaas.cloud.ibm.com/v1/instances/02c7_4838ec5d-7075-414b-aa43-b705d0e39fd1/network_attachments/02c7-442e8ba1-d8a7-4b47-bdd2-1a0f9a7fe868",
                "lifecycle_state": "stable",
                "port_speed": 6000,
                "primary_ip": [
                    {
                        "address": "10.243.64.4",
                        "deleted": [],
                        "href": "https://eu-de.private.iaas.cloud.ibm.com/v1/subnets/02c7-f27e1e0d-290b-440a-8be9-7f20ed5e333a/reserved_ips/02c7-a09981c8-5e7a-4e13-b124-7223994c13e2",
                        "id": "02c7-a09981c8-5e7a-4e13-b124-7223994c13e2",
                        "name": "manifesto-tilt-hamster-bovine",
                        "resource_type": "subnet_reserved_ip"
                    }
                ],
                "resource_type": "instance_network_attachment",
                "subnet": [
                    {
                        "crn": "crn:v1:bluemix:public:is:eu-de-2:a/3a4ef740c2d607b1331738faf667de76::subnet:02c7-f27e1e0d-290b-440a-8be9-7f20ed5e333a",
                        "deleted": [],
                        "href": "https://eu-de.private.iaas.cloud.ibm.com/v1/subnets/02c7-f27e1e0d-290b-440a-8be9-7f20ed5e333a",
                        "id": "02c7-f27e1e0d-290b-440a-8be9-7f20ed5e333a",
                        "name": "fq414-subnet-2",
                        "resource_type": "subnet"
                    }
                ],
                "type": "primary",
                "virtual_network_interface": [
                    {
                        "crn": "crn:v1:bluemix:public:is:eu-de-2:a/3a4ef740c2d607b1331738faf667de76::virtual-network-interface:02c7-8a2256bc-f079-490a-baef-6b31a9b7879d",
                        "href": "https://eu-de.private.iaas.cloud.ibm.com/v1/virtual_network_interfaces/02c7-8a2256bc-f079-490a-baef-6b31a9b7879d",
                        "id": "02c7-8a2256bc-f079-490a-baef-6b31a9b7879d",
                        "name": "overflow-operator-quill-unrevised",
                        "resource_type": "virtual_network_interface"
                    }
                ]
            }
        },
        {
            "about": {
                "access_tags": null,
                "account_id": "3a4ef740c2d607b1331738faf667de76",
                "config_type": "volume-attachment",
                "last_config_refresh_time": "2025-05-05T22:39:29.324353402Z",
                "location": "eu-de",
                "resource_crn": "crn:v1:bluemix:public:is:eu-de-2:a/3a4ef740c2d607b1331738faf667de76::instance:02c7_4838ec5d-7075-414b-aa43-b705d0e39fd1",
                "resource_group_id": "768fdf7e87f44ab2bfec4e6b910f1cfb",
                "resource_name": "undermost-strife-salvation-botany",
                "service_name": "is.instance",
                "service_tags": null,
                "type_id": "02c7-46a407aa-8369-4c8d-8c95-5b3be03194a7",
                "user_tags": null
            },
            "config": null,
            "config_v2": {
                "delete_volume_on_instance_delete": true,
                "device": "02c7-46a407aa-8369-4c8d-8c95-5b3be03194a7-lvp5p",
                "href": "https://eu-de.private.iaas.cloud.ibm.com/v1/instances/02c7_4838ec5d-7075-414b-aa43-b705d0e39fd1/volume_attachments/02c7-46a407aa-8369-4c8d-8c95-5b3be03194a7",
                "status": "attached",
                "type": "boot",
                "volume_crn": "crn:v1:bluemix:public:is:eu-de-2:a/3a4ef740c2d607b1331738faf667de76::volume:r010-80bddfd4-db50-43dd-9692-472831142df0",
                "volume_deleted": "",
                "volume_href": "https://eu-de.private.iaas.cloud.ibm.com/v1/volumes/r010-80bddfd4-db50-43dd-9692-472831142df0",
                "volume_id": "r010-80bddfd4-db50-43dd-9692-472831142df0",
                "volume_name": "fq-datastage-boot-1738601631000",
                "volume_reference": []
            }
        },
        {
            "about": {
                "access_tags": null,
                "account_id": "3a4ef740c2d607b1331738faf667de76",
                "config_type": "network-interface",
                "created_at": "2024-10-14T11:52:45.000Z",
                "last_config_refresh_time": "2025-05-05T09:00:02.723221586Z",
                "location": "eu-de",
                "resource_crn": "crn:v1:bluemix:public:is:eu-de-3:a/3a4ef740c2d607b1331738faf667de76::instance:02d7_43f05bc3-7e36-4bbe-a88d-173f83ade9b6",
                "resource_group_id": "438b802f75874f69b7a7abeb8d5269e4",
                "resource_name": "eth0",
                "service_name": "is.instance",
                "service_tags": null,
                "type_id": "02d7-f995aba9-532a-47fa-a289-6a07d80afd38",
                "user_tags": null
            },
            "config": null,
            "config_v2": {
                "allow_ip_spoofing": false,
                "floating_ips": [
                    {
                        "address": "149.81.214.25",
                        "crn": "crn:v1:bluemix:public:is:eu-de-3:a/3a4ef740c2d607b1331738faf667de76::floating-ip:r010-829d5e7d-1776-4688-832d-111cc83787d2",
                        "deleted": [],
                        "href": "https://eu-de.private.iaas.cloud.ibm.com/v1/floating_ips/r010-829d5e7d-1776-4688-832d-111cc83787d2",
                        "id": "r010-829d5e7d-1776-4688-832d-111cc83787d2",
                        "name": "billingip"
                    }
                ],
                "href": "https://eu-de.private.iaas.cloud.ibm.com/v1/instances/02d7_43f05bc3-7e36-4bbe-a88d-173f83ade9b6/network_interfaces/02d7-f995aba9-532a-47fa-a289-6a07d80afd38",
                "port_speed": 3000,
                "primary_ip": [
                    {
                        "address": "10.243.128.5",
                        "href": "https://eu-de.private.iaas.cloud.ibm.com/v1/subnets/02d7-3578f7ef-15bc-4378-81df-20c307f0dd9c/reserved_ips/02d7-4250d666-139e-4a9b-9b87-ed195de3cdfc",
                        "name": "cargo-unwound-sable-moonshine",
                        "reserved_ip": "02d7-4250d666-139e-4a9b-9b87-ed195de3cdfc",
                        "resource_type": "subnet_reserved_ip"
                    }
                ],
                "primary_ipv4_address": "10.243.128.5",
                "reserved_ips": [
                    {
                        "address": "10.243.128.5",
                        "auto_delete": true,
                        "created_at": "2024-10-14T11:52:45.000Z",
                        "href": "https://eu-de.private.iaas.cloud.ibm.com/v1/subnets/02d7-3578f7ef-15bc-4378-81df-20c307f0dd9c/reserved_ips/02d7-4250d666-139e-4a9b-9b87-ed195de3cdfc",
                        "name": "cargo-unwound-sable-moonshine",
                        "owner": "user",
                        "reserved_ip": "02d7-4250d666-139e-4a9b-9b87-ed195de3cdfc",
                        "resource_type": "subnet_reserved_ip",
                        "target": "02d7-f995aba9-532a-47fa-a289-6a07d80afd38"
                    }
                ],
                "resource_type": "network_interface",
                "security_groups": [
                    {
                        "crn": "crn:v1:bluemix:public:is:eu-de:a/3a4ef740c2d607b1331738faf667de76::security-group:r010-7dc853b1-5575-4e5a-af13-e4c6d66aa425",
                        "deleted": [],
                        "href": "https://eu-de.private.iaas.cloud.ibm.com/v1/security_groups/r010-7dc853b1-5575-4e5a-af13-e4c6d66aa425",
                        "id": "r010-7dc853b1-5575-4e5a-af13-e4c6d66aa425",
                        "name": "syndrome-primate-flinty-granular"
                    }
                ],
                "status": "available",
                "subnet": [
                    {
                        "crn": "crn:v1:bluemix:public:is:eu-de-3:a/3a4ef740c2d607b1331738faf667de76::subnet:02d7-3578f7ef-15bc-4378-81df-20c307f0dd9c",
                        "deleted": [],
                        "href": "https://eu-de.private.iaas.cloud.ibm.com/v1/subnets/02d7-3578f7ef-15bc-4378-81df-20c307f0dd9c",
                        "id": "02d7-3578f7ef-15bc-4378-81df-20c307f0dd9c",
                        "name": "sn-20241010-03"
                    }
                ],
                "type": "primary"
            }
        },
        {
            "about": {
                "access_tags": null,
                "account_id": "3a4ef740c2d607b1331738faf667de76",
                "config_type": "network-attachment",
                "created_at": "2024-10-14T11:52:45.000Z",
                "last_config_refresh_time": "2025-05-05T09:00:02.723221586Z",
                "location": "eu-de",
                "resource_crn": "crn:v1:bluemix:public:is:eu-de-3:a/3a4ef740c2d607b1331738faf667de76::instance:02d7_43f05bc3-7e36-4bbe-a88d-173f83ade9b6",
                "resource_group_id": "438b802f75874f69b7a7abeb8d5269e4",
                "resource_name": "eth0",
                "service_name": "is.instance",
                "service_tags": null,
                "type_id": "02d7-f995aba9-532a-47fa-a289-6a07d80afd38",
                "user_tags": null
            },
            "config": null,
            "config_v2": {
                "href": "https://eu-de.private.iaas.cloud.ibm.com/v1/instances/02d7_43f05bc3-7e36-4bbe-a88d-173f83ade9b6/network_attachments/02d7-f995aba9-532a-47fa-a289-6a07d80afd38",
                "lifecycle_state": "stable",
                "port_speed": 3000,
                "primary_ip": [
                    {
                        "address": "10.243.128.5",
                        "deleted": [],
                        "href": "https://eu-de.private.iaas.cloud.ibm.com/v1/subnets/02d7-3578f7ef-15bc-4378-81df-20c307f0dd9c/reserved_ips/02d7-4250d666-139e-4a9b-9b87-ed195de3cdfc",
                        "id": "02d7-4250d666-139e-4a9b-9b87-ed195de3cdfc",
                        "name": "cargo-unwound-sable-moonshine",
                        "resource_type": "subnet_reserved_ip"
                    }
                ],
                "resource_type": "instance_network_attachment",
                "subnet": [
                    {
                        "crn": "crn:v1:bluemix:public:is:eu-de-3:a/3a4ef740c2d607b1331738faf667de76::subnet:02d7-3578f7ef-15bc-4378-81df-20c307f0dd9c",
                        "deleted": [],
                        "href": "https://eu-de.private.iaas.cloud.ibm.com/v1/subnets/02d7-3578f7ef-15bc-4378-81df-20c307f0dd9c",
                        "id": "02d7-3578f7ef-15bc-4378-81df-20c307f0dd9c",
                        "name": "sn-20241010-03",
                        "resource_type": "subnet"
                    }
                ],
                "type": "primary",
                "virtual_network_interface": [
                    {
                        "crn": "crn:v1:bluemix:public:is:eu-de-3:a/3a4ef740c2d607b1331738faf667de76::virtual-network-interface:02d7-f31490d7-6106-4ccb-8966-c29d86bd44ad",
                        "href": "https://eu-de.private.iaas.cloud.ibm.com/v1/virtual_network_interfaces/02d7-f31490d7-6106-4ccb-8966-c29d86bd44ad",
                        "id": "02d7-f31490d7-6106-4ccb-8966-c29d86bd44ad",
                        "name": "extended-radiantly-reggae-raster",
                        "resource_type": "virtual_network_interface"
                    }
                ]
            }
        },
        {
            "about": {
                "access_tags": null,
                "account_id": "3a4ef740c2d607b1331738faf667de76",
                "config_type": "volume-attachment",
                "last_config_refresh_time": "2025-05-05T09:00:02.723221586Z",
                "location": "eu-de",
                "resource_crn": "crn:v1:bluemix:public:is:eu-de-3:a/3a4ef740c2d607b1331738faf667de76::instance:02d7_43f05bc3-7e36-4bbe-a88d-173f83ade9b6",
                "resource_group_id": "438b802f75874f69b7a7abeb8d5269e4",
                "resource_name": "rerun-settling-crust-lapel",
                "service_name": "is.instance",
                "service_tags": null,
                "type_id": "02d7-5f64a90e-69a6-4a6f-9d70-33e8e6911708",
                "user_tags": null
            },
            "config": null,
            "config_v2": {
                "delete_volume_on_instance_delete": true,
                "device": "02d7-5f64a90e-69a6-4a6f-9d70-33e8e6911708-z9jrs",
                "href": "https://eu-de.private.iaas.cloud.ibm.com/v1/instances/02d7_43f05bc3-7e36-4bbe-a88d-173f83ade9b6/volume_attachments/02d7-5f64a90e-69a6-4a6f-9d70-33e8e6911708",
                "status": "attached",
                "type": "boot",
                "volume_crn": "crn:v1:bluemix:public:is:eu-de-3:a/3a4ef740c2d607b1331738faf667de76::volume:r010-e58d88f9-1c13-4ddc-93e9-897ab3cef632",
                "volume_deleted": "",
                "volume_href": "https://eu-de.private.iaas.cloud.ibm.com/v1/volumes/r010-e58d88f9-1c13-4ddc-93e9-897ab3cef632",
                "volume_id": "r010-e58d88f9-1c13-4ddc-93e9-897ab3cef632",
                "volume_name": "billingcognos-boot-1728906575000",
                "volume_reference": []
            }
        }
    ]
}